dexter/__init__.py
dexter/board/__init__.py
dexter/board/aa.py
dexter/board/example.py
dexter/board/main.py
dexter/core/Invento.py
dexter/core/__init__.py
dexter/core/pipeline.py
dexter/core/scratch.py
dexter/core/simulation_pipeline.py
dexter/data_wrangling/__init__.py
dexter/data_wrangling/modifiers.py
dexter/environment/README.md
dexter/environment/__init__.py
dexter/environment/grid.py
dexter/environment/setup.py
dexter/environment/try.py
dexter/environment/tests/test_environment.py
dexter/language/__init__.py
dexter/language/FineTune/README.md
dexter/language/FineTune/app.py
dexter/language/FineTune/model.py
dexter/language/lang/__init__.py
dexter/language/lang/chains/__init__.py
dexter/language/lang/pipelines/RAGPipeline.py
dexter/language/lang/pipelines/__init__.py
dexter/language/lang/pipelines/helpers.py
dexter/ml/__init__.py
dexter/ml/pick.py
dexter/optimization/__init__.py
dexter/optimization/equation.py
dexter/optimization/problem.py
dexter/optimization/solution.py
dexter/optimization/tests/test_equation.py
dexter/optimization/tests/test_solution.py
dexter/simulation/__init__.py
dexter/simulation/sim_manager.py
dexter/stats/__init__.py
dexter/stats/distribution.py
dexter/stats/funcs.py
dexter/stats/rv.py
dexter/stats/sample.py
dexter/stats/utils.py
dexter/stats/tests/__init__.py
dexter/stats/tests/test_distr.py
dexter/stats/tests/test_rv.py
dexter/visualization/__init__.py
dexter/visualization/matrix.py
dexter/visualization/space.py
dexter/visualization/utils.py
dexter_toolkit-0.1.0.dist-info/licenses/LICENSE
dexter_toolkit-0.1.0.dist-info/METADATA
dexter_toolkit-0.1.0.dist-info/WHEEL
dexter_toolkit-0.1.0.dist-info/top_level.txt
dexter_toolkit-0.1.0.dist-info/RECORD
