Metadata-Version: 2.4
Name: dexter-toolkit
Version: 0.1.0
Summary: Data Experimentation and Tinkering Kit - A comprehensive Python toolkit for data science, machine learning, optimization, simulation, and visualization experiments
Author-email: Deniz <denizkurtaran00@gmail.com>
License-Expression: MIT
Project-URL: Homepage, https://github.com/DenizK00/Dexter
Project-URL: Documentation, https://github.com/DenizK00/Dexter#readme
Project-URL: Repository, https://github.com/DenizK00/Dexter.git
Project-URL: Bug Tracker, https://github.com/DenizK00/Dexter/issues
Project-URL: Changelog, https://github.com/DenizK00/Dexter/blob/main/CHANGELOG.md
Keywords: data-science,machine-learning,optimization,simulation,visualization,statistics
Classifier: Development Status :: 3 - Alpha
Classifier: Intended Audience :: Developers
Classifier: Intended Audience :: Science/Research
Classifier: Programming Language :: Python :: 3
Classifier: Programming Language :: Python :: 3.8
Classifier: Programming Language :: Python :: 3.9
Classifier: Programming Language :: Python :: 3.10
Classifier: Programming Language :: Python :: 3.11
Classifier: Topic :: Scientific/Engineering :: Artificial Intelligence
Classifier: Topic :: Scientific/Engineering :: Mathematics
Classifier: Topic :: Scientific/Engineering :: Visualization
Requires-Python: >=3.8
License-File: LICENSE
Requires-Dist: dash>=2.17.0
Requires-Dist: dash-bootstrap-components>=2.0.3
Requires-Dist: hyperopt>=0.2.7
Requires-Dist: ipykernel>=6.30.1
Requires-Dist: ipython>=8.12.3
Requires-Dist: jp-proxy-widget>=1.0.10
Requires-Dist: jupyter-dash>=0.4.2
Requires-Dist: langchain>=0.3.27
Requires-Dist: matplotlib>=3.10.5
Requires-Dist: numpy<2.0,>=1.21
Requires-Dist: pandas>=2.3.1
Requires-Dist: plotly>=5.9.0
Requires-Dist: pyomo>=6.9.3
Requires-Dist: PyQt5>=5.15.11
Requires-Dist: scikit-learn>=1.2.2
Requires-Dist: scipy>=1.16.1
Requires-Dist: seaborn>=0.13.2
Requires-Dist: simpy>=4.1.1
Requires-Dist: sympy>=1.12
Provides-Extra: dev
Requires-Dist: pytest>=7.0.0; extra == "dev"
Requires-Dist: pytest-cov>=4.0.0; extra == "dev"
Requires-Dist: black>=22.0.0; extra == "dev"
Requires-Dist: flake8>=5.0.0; extra == "dev"
Requires-Dist: mypy>=1.0.0; extra == "dev"
Provides-Extra: docs
Requires-Dist: sphinx>=5.0.0; extra == "docs"
Requires-Dist: sphinx-rtd-theme>=1.0.0; extra == "docs"
Dynamic: license-file
